nii_info.py
nii_info-1.0.1.dist-info/entry_points.txt
nii_info-1.0.1.dist-info/LICENSE
nii_info-1.0.1.dist-info/WHEEL
nii_info-1.0.1.dist-info/METADATA
nii_info-1.0.1.dist-info/RECORD
