Metadata-Version: 2.1
Name: nii-info
Version: 1.0.1
Summary: Display NIfTI image information in a tabular format
Home-page: https://github.com/andrewrosss/nii-info
License: MIT
Keywords: nifti,neuroimaging,neuro,cli
Author: Andrew Ross
Author-email: andrew.ross.mail@gmail.com
Requires-Python: >=3.8,<4.0
Classifier: Environment :: Console
Classifier: Intended Audience :: Developers
Classifier: License :: OSI Approved :: MIT License
Classifier: Operating System :: OS Independent
Classifier: Programming Language :: Python :: 3
Classifier: Programming Language :: Python :: 3.0
Classifier: Programming Language :: Python :: 3.10
Classifier: Programming Language :: Python :: 3.8
Classifier: Programming Language :: Python :: 3.9
Classifier: Topic :: Software Development :: Libraries :: Python Modules
Classifier: Topic :: Software Development :: User Interfaces
Classifier: Topic :: Utilities
Classifier: Typing :: Typed
Requires-Dist: nibabel (>=3.0.0,<4.0.0)
Project-URL: Documentation, https://github.com/andrewrosss/nii-info
Project-URL: Repository, https://github.com/andrewrosss/nii-info
